Metadata-Version: 2.1
Name: selectable-box-list
Version: 1.0.3
Summary: Dash Selectable Box List Component
Author: s_matsumoto s_matsumoto@thinkup-sol.co.jp
License: MIT
License-File: LICENSE
